ctftools/__init__.py
ctftools/aestools.py
ctftools/rsatools.py
ctftools/utils.py
ctftools/xortools.py
ctftools/data/english_words.txt
ctftools-0.1.2.dist-info/LICENSE
ctftools-0.1.2.dist-info/METADATA
ctftools-0.1.2.dist-info/WHEEL
ctftools-0.1.2.dist-info/top_level.txt
ctftools-0.1.2.dist-info/RECORD
