Metadata-Version: 2.1
Name: ctftools
Version: 0.1.2
Summary: A small collection of tools for solving CTF challenges
Home-page: https://github.com/pietroferretti/ctftools
Author: Pietro Ferretti
Author-email: me@pietroferretti.com
License: MIT
Project-URL: Source, https://github.com/pietroferretti/ctftools
Keywords: ctf security cryptography
Platform: UNKNOWN
Classifier: Development Status :: 4 - Beta
Classifier: Programming Language :: Python :: 2
Classifier: Programming Language :: Python :: 2.7
Classifier: Programming Language :: Python :: 3
Classifier: Programming Language :: Python :: 3.4
Classifier: Programming Language :: Python :: 3.5
Classifier: Programming Language :: Python :: 3.6
Classifier: Programming Language :: Python :: 3.7
Classifier: License :: OSI Approved :: MIT License
Classifier: Operating System :: OS Independent
Classifier: Topic :: Security
Classifier: Topic :: Security :: Cryptography
Requires-Dist: six
Provides-Extra: tests
Requires-Dist: pytest ; extra == 'tests'
Requires-Dist: pycrypto ; extra == 'tests'
